chronium/multistealer.py
chronium/modules/__init__.py
chronium/modules/chromium.py
chronium/modules/discord.py
chronium/modules/system.py
chronium/utils/__init__.py
chronium/utils/autostart.py
chronium/utils/config.py
chronium/utils/multipart.py
chronium/utils/sender.py
chronium-0.0.1.dist-info/METADATA
chronium-0.0.1.dist-info/WHEEL
chronium-0.0.1.dist-info/top_level.txt
chronium-0.0.1.dist-info/RECORD
